gte_py/__init__.py
gte_py/api/__init__.py
gte_py/api/chain/__init__.py
gte_py/api/chain/abi/clob.json
gte_py/api/chain/abi/clob_factory.json
gte_py/api/chain/abi/clob_manager.json
gte_py/api/chain/abi/erc20.json
gte_py/api/chain/abi/launchpad.json
gte_py/api/chain/abi/router.json
gte_py/api/chain/abi/weth.json
gte_py/api/chain/clob.py
gte_py/api/chain/clob_factory.py
gte_py/api/chain/clob_manager.py
gte_py/api/chain/erc20.py
gte_py/api/chain/event_source.py
gte_py/api/chain/events.py
gte_py/api/chain/launchpad.py
gte_py/api/chain/router.py
gte_py/api/chain/structs.py
gte_py/api/chain/utils.py
gte_py/api/chain/weth.py
gte_py/api/openapi/__init__.py
gte_py/api/openapi/api/__init__.py
gte_py/api/openapi/api/default_api.py
gte_py/api/openapi/api/markets_api.py
gte_py/api/openapi/api/tokens_api.py
gte_py/api/openapi/api/users_api.py
gte_py/api/openapi/api_client.py
gte_py/api/openapi/api_response.py
gte_py/api/openapi/configuration.py
gte_py/api/openapi/exceptions.py
gte_py/api/openapi/models/__init__.py
gte_py/api/openapi/models/basic_order.py
gte_py/api/openapi/models/book.py
gte_py/api/openapi/models/book_level.py
gte_py/api/openapi/models/candle.py
gte_py/api/openapi/models/candle_interval.py
gte_py/api/openapi/models/error_response.py
gte_py/api/openapi/models/filled_order.py
gte_py/api/openapi/models/get_token_list_response_inner.py
gte_py/api/openapi/models/get_user_portfolio_response.py
gte_py/api/openapi/models/gte_info_response.py
gte_py/api/openapi/models/lp_position.py
gte_py/api/openapi/models/market.py
gte_py/api/openapi/models/market_type.py
gte_py/api/openapi/models/open_order.py
gte_py/api/openapi/models/order.py
gte_py/api/openapi/models/order_side.py
gte_py/api/openapi/models/order_status.py
gte_py/api/openapi/models/order_type.py
gte_py/api/openapi/models/server_health_response.py
gte_py/api/openapi/models/token.py
gte_py/api/openapi/models/token_balance.py
gte_py/api/openapi/models/token_metadata.py
gte_py-0.1.3.dist-info/WHEEL
gte_py-0.1.3.dist-info/entry_points.txt
gte_py-0.1.3.dist-info/METADATA
gte_py-0.1.3.dist-info/RECORD
