Metadata-Version: 2.4
Name: gte-py
Version: 0.1.3
Summary: GTE Python SDK
Author: Jakku Sakura, moses
Author-email: Jakku Sakura <jakku.sakura@auros.global>, moses <moses@liquidlabs.com>
License-Expression: MIT
Requires-Dist: typer>=0.9.0
Requires-Dist: aiohttp>=3.8.0
Requires-Dist: web3~=7.10.0
Requires-Dist: urllib3~=1.26
Requires-Dist: dateutils
Requires-Python: >=3.10
